qnas/__init__.py
qnas/anharmonicity.py
qnas/collapseOperatorFunction.py
qnas/envelopeFunction.py
qnas/gateFuncs.py
qnas/gateLib.py
qnas/help.py
qnas/mainAlgorithm.py
qnas/mcSolving.py
qnas/openqasmInterpreter.py
qnas/qubitClass.py
qnas/readData.py
qnas/solve.py
qnas/storeTimeDynamicsMain.py
qnas/zzInteractionFunction.py
qnas-1.0.0.dist-info/LICENSE.txt
qnas-1.0.0.dist-info/METADATA
qnas-1.0.0.dist-info/WHEEL
qnas-1.0.0.dist-info/top_level.txt
qnas-1.0.0.dist-info/RECORD
