Metadata-Version: 2.1
Name: qnas
Version: 1.0.0
Summary: QnAS package
Home-page: https://github.com/isakwi/Kandidatarbete/tree/main/qnas
Author: Isak Wikman, Edvin Martinson, Axel Blom, Albin Edenmyr, Didrik Palmqvist, Ludvig Nordqvist
Author-email: isakwi@student.chalmers.se, edvmar@student.chalmers.se, bloaxel@student.chalmers.se, edenmyr@student.chalmers.se, didrikp@student.chalmers.se, ludnor@student.chalmers.se
License: MIT
Keywords: pypi,qnas,algorithm-simulator,quantum,quantum-algorithm-simulator,algorithm,noise,simulator
Classifier: Development Status :: 3 - Alpha
Classifier: Topic :: Software Development :: Documentation
Classifier: License :: OSI Approved :: MIT License
Classifier: Programming Language :: Python :: 3
Requires-Python: >=3.9
License-File: LICENSE.txt
Requires-Dist: numpy
Requires-Dist: qutip
Requires-Dist: qiskit
Requires-Dist: pandas
Requires-Dist: regex
